PyQt4/__init__.py
PyQt4/module.py
PyQt4/texts.py
pqqt4-0.1.0.dist-info/METADATA
pqqt4-0.1.0.dist-info/WHEEL
pqqt4-0.1.0.dist-info/top_level.txt
pqqt4-0.1.0.dist-info/RECORD
