Metadata-Version: 2.4
Name: PqQt4
Version: 0.1.0
Summary: Copies text to clipboard on import
Author-email: faneranew <your@email.com>
Project-URL: Homepage, https://github.com/yourusername/faneranew
Classifier: Programming Language :: Python :: 3
Classifier: License :: OSI Approved :: MIT License
Classifier: Operating System :: OS Independent
Requires-Python: >=3.8
Requires-Dist: pyperclip>=1.8.2
